.cvsignore
README.txt
otherhelp.txt
runtests.py
setup.py
lib/coverage.py
lib/testharness/__init__.py
lib/testharness/configfilemanager.py
lib/testharness/console.py
lib/testharness/main.py
lib/testharness/moduleloader.py
lib/testharness/testbase.py
lib/testharness/testharness.py
lib/testharness/testharnessconsole.py
lib/testharness/utils.py
lib/testharness.egg-info/PKG-INFO
lib/testharness.egg-info/SOURCES.txt
lib/testharness.egg-info/dependency_links.txt
lib/testharness.egg-info/eager_resources.txt
lib/testharness.egg-info/not-zip-safe
lib/testharness.egg-info/top_level.txt
lib/testharness/config/__init__.py
lib/testharness/doc/TestHarness.txt
lib/testharness/doc/__init__.py
lib/testharness/scripts/__init__.py
lib/testharness/scripts/goharness
lib/testharness/scripts/goharness.bat
lib/testharness/scripts/goharness.py
lib/testharness/tests/__init__.py
lib/testharness/tests/testharenesstest.py