Metadata-Version: 1.0
Name: testharness
Version: 1.0.5
Summary: This is intended to be used as a generic functional test framework.
Home-page: UNKNOWN
Author: Oisin Mulvihill
Author-email: oisin mulvihill at gmail com
License: LGPL
Platform: UNKNOWN
